README.md
setup.py
metadata/__docs.py
metadata/__init__.py
museotoolbox/__init__.py
museotoolbox.egg-info/PKG-INFO
museotoolbox.egg-info/SOURCES.txt
museotoolbox.egg-info/dependency_links.txt
museotoolbox.egg-info/not-zip-safe
museotoolbox.egg-info/requires.txt
museotoolbox.egg-info/top_level.txt
museotoolbox/ai/__init__.py
museotoolbox/charts/__init__.py
museotoolbox/cross_validation/__init__.py
museotoolbox/cross_validation/_sample_selection.py
museotoolbox/datasets/__init__.py
museotoolbox/datasets/_historicalmap/map_compress.tif
museotoolbox/datasets/_historicalmap/map_lowres.tif
museotoolbox/datasets/_historicalmap/train.gpkg
museotoolbox/datasets/_historicalmap/train_centroid.gpkg
museotoolbox/internal_tools/__init__.py
museotoolbox/processing/__init__.py
museotoolbox/stats/__init__.py
test/__init__.py
test/test_ai.py
test/test_charts.py
test/test_cross_validation.py
test/test_processing.py
test/test_stats.py