Metadata-Version: 2.1
Name: museotoolbox
Version: 0.13.2
Summary: Raster and vector tools for Remote Sensing and Classification, built upon gdal library
Home-page: https://github.com/nkarasiak/MuseoToolBox
Author: Nicolas Karasiak
Author-email: karasiak.nicolas@gmail.com
License: GPLv3
Platform: UNKNOWN
Classifier: Topic :: Scientific/Engineering :: Artificial Intelligence
Classifier: Topic :: Scientific/Engineering :: GIS
Classifier: Programming Language :: Python :: 3
Classifier: Intended Audience :: Science/Research
